[
  {
    "id": "1001",
    "jiajuName": "老旧方木桌",
    "jiajuType": "1",
    "jiajuacrtivatePrice": "100",
    "jiajuislock": "1",
    "imgname": "img_jiaju1_1",
    "koubeizhi": "10"
  },
  {
    "id": "1002",
    "jiajuName": "简约方桌",
    "jiajuType": "1",
    "jiajuacrtivatePrice": "600",
    "jiajuislock": "1",
    "imgname": "img_jiaju1_2",
    "koubeizhi": "20"
  },
  {
    "id": "1003",
    "jiajuName": "现代方桌",
    "jiajuType": "1",
    "jiajuacrtivatePrice": "1100",
    "jiajuislock": "0",
    "imgname": "img_jiaju1_3",
    "koubeizhi": "30"
  },
  {
    "id": "1004",
    "jiajuName": "石墨方桌",
    "jiajuType": "1",
    "jiajuacrtivatePrice": "1600",
    "jiajuislock": "0",
    "imgname": "img_jiaju1_4",
    "koubeizhi": "40"
  },
  {
    "id": "1005",
    "jiajuName": "红木方桌",
    "jiajuType": "1",
    "jiajuacrtivatePrice": "2100",
    "jiajuislock": "2",
    "imgname": "img_jiaju1_5",
    "koubeizhi": "50"
  },
  {
    "id": "1006",
    "jiajuName": "喜庆方桌",
    "jiajuType": "1",
    "jiajuacrtivatePrice": "2600",
    "jiajuislock": "2",
    "imgname": "img_jiaju1_6",
    "koubeizhi": "60"
  },
  {
    "id": "2001",
    "jiajuName": "老旧圆桌",
    "jiajuType": "2",
    "jiajuacrtivatePrice": "200",
    "jiajuislock": "1",
    "imgname": "img_jiaju2_1",
    "koubeizhi": "20"
  },
  {
    "id": "2002",
    "jiajuName": "简约圆桌",
    "jiajuType": "2",
    "jiajuacrtivatePrice": "900",
    "jiajuislock": "1",
    "imgname": "img_jiaju2_2",
    "koubeizhi": "30"
  },
  {
    "id": "2003",
    "jiajuName": "现代圆桌",
    "jiajuType": "2",
    "jiajuacrtivatePrice": "1600",
    "jiajuislock": "0",
    "imgname": "img_jiaju2_3",
    "koubeizhi": "40"
  },
  {
    "id": "2004",
    "jiajuName": "石墨圆桌",
    "jiajuType": "2",
    "jiajuacrtivatePrice": "2300",
    "jiajuislock": "0",
    "imgname": "img_jiaju2_4",
    "koubeizhi": "50"
  },
  {
    "id": "2005",
    "jiajuName": "红木圆桌",
    "jiajuType": "2",
    "jiajuacrtivatePrice": "3000",
    "jiajuislock": "2",
    "imgname": "img_jiaju2_5",
    "koubeizhi": "60"
  },
  {
    "id": "2006",
    "jiajuName": "喜庆圆桌",
    "jiajuType": "2",
    "jiajuacrtivatePrice": "3700",
    "jiajuislock": "2",
    "imgname": "img_jiaju2_6",
    "koubeizhi": "70"
  },
  {
    "id": "3001",
    "jiajuName": "老旧长桌",
    "jiajuType": "3",
    "jiajuacrtivatePrice": "150",
    "jiajuislock": "1",
    "imgname": "img_jiaju3_1",
    "koubeizhi": "15"
  },
  {
    "id": "3002",
    "jiajuName": "简约长桌",
    "jiajuType": "3",
    "jiajuacrtivatePrice": "750",
    "jiajuislock": "1",
    "imgname": "img_jiaju3_2",
    "koubeizhi": "20"
  },
  {
    "id": "3003",
    "jiajuName": "现代长桌",
    "jiajuType": "3",
    "jiajuacrtivatePrice": "1350",
    "jiajuislock": "0",
    "imgname": "img_jiaju3_3",
    "koubeizhi": "25"
  },
  {
    "id": "3004",
    "jiajuName": "石墨长桌",
    "jiajuType": "3",
    "jiajuacrtivatePrice": "1950",
    "jiajuislock": "0",
    "imgname": "img_jiaju3_4",
    "koubeizhi": "30"
  },
  {
    "id": "3005",
    "jiajuName": "红木长桌",
    "jiajuType": "3",
    "jiajuacrtivatePrice": "2550",
    "jiajuislock": "2",
    "imgname": "img_jiaju3_5",
    "koubeizhi": "35"
  },
  {
    "id": "3006",
    "jiajuName": "喜庆长桌",
    "jiajuType": "3",
    "jiajuacrtivatePrice": "3150",
    "jiajuislock": "2",
    "imgname": "img_jiaju3_6",
    "koubeizhi": "40"
  },
  {
    "id": "4001",
    "jiajuName": "老旧双人桌",
    "jiajuType": "4",
    "jiajuacrtivatePrice": "100",
    "jiajuislock": "1",
    "imgname": "img_jiaju4_1",
    "koubeizhi": "10"
  },
  {
    "id": "4002",
    "jiajuName": "简约双人桌",
    "jiajuType": "4",
    "jiajuacrtivatePrice": "600",
    "jiajuislock": "1",
    "imgname": "img_jiaju4_2",
    "koubeizhi": "20"
  },
  {
    "id": "4003",
    "jiajuName": "现代双人桌",
    "jiajuType": "4",
    "jiajuacrtivatePrice": "1100",
    "jiajuislock": "0",
    "imgname": "img_jiaju4_3",
    "koubeizhi": "30"
  },
  {
    "id": "4004",
    "jiajuName": "石墨双人桌",
    "jiajuType": "4",
    "jiajuacrtivatePrice": "1600",
    "jiajuislock": "0",
    "imgname": "img_jiaju4_4",
    "koubeizhi": "40"
  },
  {
    "id": "4005",
    "jiajuName": "红木双人桌",
    "jiajuType": "4",
    "jiajuacrtivatePrice": "2100",
    "jiajuislock": "2",
    "imgname": "img_jiaju4_5",
    "koubeizhi": "50"
  },
  {
    "id": "4006",
    "jiajuName": "喜庆双人桌",
    "jiajuType": "4",
    "jiajuacrtivatePrice": "2600",
    "jiajuislock": "2",
    "imgname": "img_jiaju4_6",
    "koubeizhi": "60"
  }
]